siti/__init__.py
siti/__main__.py
siti-1.4.5.dist-info/LICENSE.md
siti-1.4.5.dist-info/METADATA
siti-1.4.5.dist-info/WHEEL
siti-1.4.5.dist-info/entry_points.txt
siti-1.4.5.dist-info/top_level.txt
siti-1.4.5.dist-info/RECORD
