Metadata-Version: 2.1
Name: siti
Version: 1.4.5
Summary: Calculate Spatial Information / Temporal Information according to ITU-T P.910
Home-page: https://github.com/slhck/siti
Author: Werner Robitza
Author-email: werner.robitza@gmail.com
License: MIT
Keywords: video,spatial information,temporal information
Platform: UNKNOWN
Classifier: Development Status :: 4 - Beta
Classifier: Intended Audience :: Developers
Classifier: Topic :: Multimedia :: Video
Classifier: License :: OSI Approved :: MIT License
Classifier: Natural Language :: English
Classifier: Programming Language :: Python :: 3
Classifier: Programming Language :: Python :: 3.7
Classifier: Programming Language :: Python :: 3.8
Classifier: Programming Language :: Python :: 3.9
Requires-Python: >=3.7
License-File: LICENSE.md
Requires-Dist: scipy
Requires-Dist: numpy
Requires-Dist: av
Requires-Dist: tqdm
